{"nodes": [{"id": "c_users_maju_desktop_stocks_main_stocks_main_client_src_components_addhamalimodal_tsx", "label": "AddHamaliModal.tsx", "file_type": "code", "source_file": "C:\\Users\\maju\\Desktop\\stocks-main\\stocks-main\\client\\src\\components\\AddHamaliModal.tsx", "source_location": "L1"}, {"id": "addhamalimodal_fetchrates", "label": "fetchRates()", "file_type": "code", "source_file": "C:\\Users\\maju\\Desktop\\stocks-main\\stocks-main\\client\\src\\components\\AddHamaliModal.tsx", "source_location": "L215"}, {"id": "addhamalimodal_calculateloadingtotal", "label": "calculateLoadingTotal()", "file_type": "code", "source_file": "C:\\Users\\maju\\Desktop\\stocks-main\\stocks-main\\client\\src\\components\\AddHamaliModal.tsx", "source_location": "L230"}, {"id": "addhamalimodal_calculateunloadingtotal", "label": "calculateUnloadingTotal()", "file_type": "code", "source_file": "C:\\Users\\maju\\Desktop\\stocks-main\\stocks-main\\client\\src\\components\\AddHamaliModal.tsx", "source_location": "L235"}, {"id": "addhamalimodal_calculateloosetotal", "label": "calculateLooseTotal()", "file_type": "code", "source_file": "C:\\Users\\maju\\Desktop\\stocks-main\\stocks-main\\client\\src\\components\\AddHamaliModal.tsx", "source_location": "L241"}, {"id": "addhamalimodal_handleunloadingtypechange", "label": "handleUnloadingTypeChange()", "file_type": "code", "source_file": "C:\\Users\\maju\\Desktop\\stocks-main\\stocks-main\\client\\src\\components\\AddHamaliModal.tsx", "source_location": "L246"}, {"id": "addhamalimodal_handlesave", "label": "handleSave()", "file_type": "code", "source_file": "C:\\Users\\maju\\Desktop\\stocks-main\\stocks-main\\client\\src\\components\\AddHamaliModal.tsx", "source_location": "L256"}], "edges": [{"source": "c_users_maju_desktop_stocks_main_stocks_main_client_src_components_addhamalimodal_tsx", "target": "react", "relation": "imports_from", "confidence": "EXTRACTED", "source_file": "C:\\Users\\maju\\Desktop\\stocks-main\\stocks-main\\client\\src\\components\\AddHamaliModal.tsx", "source_location": "L1", "weight": 1.0}, {"source": "c_users_maju_desktop_stocks_main_stocks_main_client_src_components_addhamalimodal_tsx", "target": "styled_components", "relation": "imports_from", "confidence": "EXTRACTED", "source_file": "C:\\Users\\maju\\Desktop\\stocks-main\\stocks-main\\client\\src\\components\\AddHamaliModal.tsx", "source_location": "L2", "weight": 1.0}, {"source": "c_users_maju_desktop_stocks_main_stocks_main_client_src_components_addhamalimodal_tsx", "target": "axios", "relation": "imports_from", "confidence": "EXTRACTED", "source_file": "C:\\Users\\maju\\Desktop\\stocks-main\\stocks-main\\client\\src\\components\\AddHamaliModal.tsx", "source_location": "L3", "weight": 1.0}, {"source": "c_users_maju_desktop_stocks_main_stocks_main_client_src_components_addhamalimodal_tsx", "target": "c_users_maju_desktop_stocks_main_stocks_main_client_src_utils_toast", "relation": "imports_from", "confidence": "EXTRACTED", "source_file": "C:\\Users\\maju\\Desktop\\stocks-main\\stocks-main\\client\\src\\components\\AddHamaliModal.tsx", "source_location": "L4", "weight": 1.0}, {"source": "c_users_maju_desktop_stocks_main_stocks_main_client_src_components_addhamalimodal_tsx", "target": "addhamalimodal_fetchrates", "relation": "contains", "confidence": "EXTRACTED", "source_file": "C:\\Users\\maju\\Desktop\\stocks-main\\stocks-main\\client\\src\\components\\AddHamaliModal.tsx", "source_location": "L215", "weight": 1.0}, {"source": "c_users_maju_desktop_stocks_main_stocks_main_client_src_components_addhamalimodal_tsx", "target": "addhamalimodal_calculateloadingtotal", "relation": "contains", "confidence": "EXTRACTED", "source_file": "C:\\Users\\maju\\Desktop\\stocks-main\\stocks-main\\client\\src\\components\\AddHamaliModal.tsx", "source_location": "L230", "weight": 1.0}, {"source": "c_users_maju_desktop_stocks_main_stocks_main_client_src_components_addhamalimodal_tsx", "target": "addhamalimodal_calculateunloadingtotal", "relation": "contains", "confidence": "EXTRACTED", "source_file": "C:\\Users\\maju\\Desktop\\stocks-main\\stocks-main\\client\\src\\components\\AddHamaliModal.tsx", "source_location": "L235", "weight": 1.0}, {"source": "c_users_maju_desktop_stocks_main_stocks_main_client_src_components_addhamalimodal_tsx", "target": "addhamalimodal_calculateloosetotal", "relation": "contains", "confidence": "EXTRACTED", "source_file": "C:\\Users\\maju\\Desktop\\stocks-main\\stocks-main\\client\\src\\components\\AddHamaliModal.tsx", "source_location": "L241", "weight": 1.0}, {"source": "c_users_maju_desktop_stocks_main_stocks_main_client_src_components_addhamalimodal_tsx", "target": "addhamalimodal_handleunloadingtypechange", "relation": "contains", "confidence": "EXTRACTED", "source_file": "C:\\Users\\maju\\Desktop\\stocks-main\\stocks-main\\client\\src\\components\\AddHamaliModal.tsx", "source_location": "L246", "weight": 1.0}, {"source": "c_users_maju_desktop_stocks_main_stocks_main_client_src_components_addhamalimodal_tsx", "target": "addhamalimodal_handlesave", "relation": "contains", "confidence": "EXTRACTED", "source_file": "C:\\Users\\maju\\Desktop\\stocks-main\\stocks-main\\client\\src\\components\\AddHamaliModal.tsx", "source_location": "L256", "weight": 1.0}], "raw_calls": [{"caller_nid": "addhamalimodal_fetchrates", "callee": "getItem", "source_file": "C:\\Users\\maju\\Desktop\\stocks-main\\stocks-main\\client\\src\\components\\AddHamaliModal.tsx", "source_location": "L217"}, {"caller_nid": "addhamalimodal_fetchrates", "callee": "await axios.get", "source_file": "C:\\Users\\maju\\Desktop\\stocks-main\\stocks-main\\client\\src\\components\\AddHamaliModal.tsx", "source_location": "L218"}, {"caller_nid": "addhamalimodal_fetchrates", "callee": "setRates", "source_file": "C:\\Users\\maju\\Desktop\\stocks-main\\stocks-main\\client\\src\\components\\AddHamaliModal.tsx", "source_location": "L221"}, {"caller_nid": "addhamalimodal_fetchrates", "callee": "error", "source_file": "C:\\Users\\maju\\Desktop\\stocks-main\\stocks-main\\client\\src\\components\\AddHamaliModal.tsx", "source_location": "L223"}, {"caller_nid": "addhamalimodal_fetchrates", "callee": "error", "source_file": "C:\\Users\\maju\\Desktop\\stocks-main\\stocks-main\\client\\src\\components\\AddHamaliModal.tsx", "source_location": "L224"}, {"caller_nid": "addhamalimodal_fetchrates", "callee": "setLoading", "source_file": "C:\\Users\\maju\\Desktop\\stocks-main\\stocks-main\\client\\src\\components\\AddHamaliModal.tsx", "source_location": "L226"}, {"caller_nid": "addhamalimodal_calculateloadingtotal", "callee": "toFixed", "source_file": "C:\\Users\\maju\\Desktop\\stocks-main\\stocks-main\\client\\src\\components\\AddHamaliModal.tsx", "source_location": "L232"}, {"caller_nid": "addhamalimodal_calculateunloadingtotal", "callee": "toFixed", "source_file": "C:\\Users\\maju\\Desktop\\stocks-main\\stocks-main\\client\\src\\components\\AddHamaliModal.tsx", "source_location": "L238"}, {"caller_nid": "addhamalimodal_calculateloosetotal", "callee": "toFixed", "source_file": "C:\\Users\\maju\\Desktop\\stocks-main\\stocks-main\\client\\src\\components\\AddHamaliModal.tsx", "source_location": "L243"}, {"caller_nid": "addhamalimodal_calculateloosetotal", "callee": "parseFloat", "source_file": "C:\\Users\\maju\\Desktop\\stocks-main\\stocks-main\\client\\src\\components\\AddHamaliModal.tsx", "source_location": "L243"}, {"caller_nid": "addhamalimodal_handleunloadingtypechange", "callee": "setUnloadingType", "source_file": "C:\\Users\\maju\\Desktop\\stocks-main\\stocks-main\\client\\src\\components\\AddHamaliModal.tsx", "source_location": "L248"}, {"caller_nid": "addhamalimodal_handleunloadingtypechange", "callee": "setHasUnloadingHamali", "source_file": "C:\\Users\\maju\\Desktop\\stocks-main\\stocks-main\\client\\src\\components\\AddHamaliModal.tsx", "source_location": "L249"}, {"caller_nid": "addhamalimodal_handleunloadingtypechange", "callee": "setUnloadingType", "source_file": "C:\\Users\\maju\\Desktop\\stocks-main\\stocks-main\\client\\src\\components\\AddHamaliModal.tsx", "source_location": "L251"}, {"caller_nid": "addhamalimodal_handleunloadingtypechange", "callee": "setHasUnloadingHamali", "source_file": "C:\\Users\\maju\\Desktop\\stocks-main\\stocks-main\\client\\src\\components\\AddHamaliModal.tsx", "source_location": "L252"}, {"caller_nid": "addhamalimodal_handlesave", "callee": "error", "source_file": "C:\\Users\\maju\\Desktop\\stocks-main\\stocks-main\\client\\src\\components\\AddHamaliModal.tsx", "source_location": "L259"}, {"caller_nid": "addhamalimodal_handlesave", "callee": "parseFloat", "source_file": "C:\\Users\\maju\\Desktop\\stocks-main\\stocks-main\\client\\src\\components\\AddHamaliModal.tsx", "source_location": "L263"}, {"caller_nid": "addhamalimodal_handlesave", "callee": "error", "source_file": "C:\\Users\\maju\\Desktop\\stocks-main\\stocks-main\\client\\src\\components\\AddHamaliModal.tsx", "source_location": "L264"}, {"caller_nid": "addhamalimodal_handlesave", "callee": "getItem", "source_file": "C:\\Users\\maju\\Desktop\\stocks-main\\stocks-main\\client\\src\\components\\AddHamaliModal.tsx", "source_location": "L269"}, {"caller_nid": "addhamalimodal_handlesave", "callee": "parseInt", "source_file": "C:\\Users\\maju\\Desktop\\stocks-main\\stocks-main\\client\\src\\components\\AddHamaliModal.tsx", "source_location": "L276"}, {"caller_nid": "addhamalimodal_handlesave", "callee": "post", "source_file": "C:\\Users\\maju\\Desktop\\stocks-main\\stocks-main\\client\\src\\components\\AddHamaliModal.tsx", "source_location": "L279"}, {"caller_nid": "addhamalimodal_handlesave", "callee": "success", "source_file": "C:\\Users\\maju\\Desktop\\stocks-main\\stocks-main\\client\\src\\components\\AddHamaliModal.tsx", "source_location": "L283"}, {"caller_nid": "addhamalimodal_handlesave", "callee": "onSuccess", "source_file": "C:\\Users\\maju\\Desktop\\stocks-main\\stocks-main\\client\\src\\components\\AddHamaliModal.tsx", "source_location": "L284"}, {"caller_nid": "addhamalimodal_handlesave", "callee": "onClose", "source_file": "C:\\Users\\maju\\Desktop\\stocks-main\\stocks-main\\client\\src\\components\\AddHamaliModal.tsx", "source_location": "L285"}, {"caller_nid": "addhamalimodal_handlesave", "callee": "error", "source_file": "C:\\Users\\maju\\Desktop\\stocks-main\\stocks-main\\client\\src\\components\\AddHamaliModal.tsx", "source_location": "L287"}, {"caller_nid": "addhamalimodal_handlesave", "callee": "error", "source_file": "C:\\Users\\maju\\Desktop\\stocks-main\\stocks-main\\client\\src\\components\\AddHamaliModal.tsx", "source_location": "L288"}]}