{"nodes": [{"id": "c_users_maju_desktop_stocks_main_stocks_main_client_src_utils_paltidisplayhelpers_ts", "label": "paltiDisplayHelpers.ts", "file_type": "code", "source_file": "C:\\Users\\maju\\Desktop\\stocks-main\\stocks-main\\client\\src\\utils\\paltiDisplayHelpers.ts", "source_location": "L1"}, {"id": "paltidisplayhelpers_getshortagedisplay", "label": "getShortageDisplay()", "file_type": "code", "source_file": "C:\\Users\\maju\\Desktop\\stocks-main\\stocks-main\\client\\src\\utils\\paltiDisplayHelpers.ts", "source_location": "L12"}, {"id": "paltidisplayhelpers_getpackagingdisplay", "label": "getPackagingDisplay()", "file_type": "code", "source_file": "C:\\Users\\maju\\Desktop\\stocks-main\\stocks-main\\client\\src\\utils\\paltiDisplayHelpers.ts", "source_location": "L33"}, {"id": "paltidisplayhelpers_getbillnumberdisplay", "label": "getBillNumberDisplay()", "file_type": "code", "source_file": "C:\\Users\\maju\\Desktop\\stocks-main\\stocks-main\\client\\src\\utils\\paltiDisplayHelpers.ts", "source_location": "L63"}, {"id": "paltidisplayhelpers_getlorrynumberdisplay", "label": "getLorryNumberDisplay()", "file_type": "code", "source_file": "C:\\Users\\maju\\Desktop\\stocks-main\\stocks-main\\client\\src\\utils\\paltiDisplayHelpers.ts", "source_location": "L75"}, {"id": "paltidisplayhelpers_getvarietydisplay", "label": "getVarietyDisplay()", "file_type": "code", "source_file": "C:\\Users\\maju\\Desktop\\stocks-main\\stocks-main\\client\\src\\utils\\paltiDisplayHelpers.ts", "source_location": "L86"}, {"id": "paltidisplayhelpers_getbagsdisplay", "label": "getBagsDisplay()", "file_type": "code", "source_file": "C:\\Users\\maju\\Desktop\\stocks-main\\stocks-main\\client\\src\\utils\\paltiDisplayHelpers.ts", "source_location": "L93"}, {"id": "paltidisplayhelpers_getquantitydisplay", "label": "getQuantityDisplay()", "file_type": "code", "source_file": "C:\\Users\\maju\\Desktop\\stocks-main\\stocks-main\\client\\src\\utils\\paltiDisplayHelpers.ts", "source_location": "L115"}, {"id": "paltidisplayhelpers_getlocationdisplay", "label": "getLocationDisplay()", "file_type": "code", "source_file": "C:\\Users\\maju\\Desktop\\stocks-main\\stocks-main\\client\\src\\utils\\paltiDisplayHelpers.ts", "source_location": "L123"}, {"id": "paltidisplayhelpers_getmovementtypedisplay", "label": "getMovementTypeDisplay()", "file_type": "code", "source_file": "C:\\Users\\maju\\Desktop\\stocks-main\\stocks-main\\client\\src\\utils\\paltiDisplayHelpers.ts", "source_location": "L134"}, {"id": "paltidisplayhelpers_getrowbackgroundcolor", "label": "getRowBackgroundColor()", "file_type": "code", "source_file": "C:\\Users\\maju\\Desktop\\stocks-main\\stocks-main\\client\\src\\utils\\paltiDisplayHelpers.ts", "source_location": "L154"}, {"id": "paltidisplayhelpers_ispaltimovement", "label": "isPaltiMovement()", "file_type": "code", "source_file": "C:\\Users\\maju\\Desktop\\stocks-main\\stocks-main\\client\\src\\utils\\paltiDisplayHelpers.ts", "source_location": "L170"}, {"id": "paltidisplayhelpers_getpaltidisplaydata", "label": "getPaltiDisplayData()", "file_type": "code", "source_file": "C:\\Users\\maju\\Desktop\\stocks-main\\stocks-main\\client\\src\\utils\\paltiDisplayHelpers.ts", "source_location": "L177"}], "edges": [{"source": "c_users_maju_desktop_stocks_main_stocks_main_client_src_utils_paltidisplayhelpers_ts", "target": "paltidisplayhelpers_getshortagedisplay", "relation": "contains", "confidence": "EXTRACTED", "source_file": "C:\\Users\\maju\\Desktop\\stocks-main\\stocks-main\\client\\src\\utils\\paltiDisplayHelpers.ts", "source_location": "L12", "weight": 1.0}, {"source": "c_users_maju_desktop_stocks_main_stocks_main_client_src_utils_paltidisplayhelpers_ts", "target": "paltidisplayhelpers_getpackagingdisplay", "relation": "contains", "confidence": "EXTRACTED", "source_file": "C:\\Users\\maju\\Desktop\\stocks-main\\stocks-main\\client\\src\\utils\\paltiDisplayHelpers.ts", "source_location": "L33", "weight": 1.0}, {"source": "c_users_maju_desktop_stocks_main_stocks_main_client_src_utils_paltidisplayhelpers_ts", "target": "paltidisplayhelpers_getbillnumberdisplay", "relation": "contains", "confidence": "EXTRACTED", "source_file": "C:\\Users\\maju\\Desktop\\stocks-main\\stocks-main\\client\\src\\utils\\paltiDisplayHelpers.ts", "source_location": "L63", "weight": 1.0}, {"source": "c_users_maju_desktop_stocks_main_stocks_main_client_src_utils_paltidisplayhelpers_ts", "target": "paltidisplayhelpers_getlorrynumberdisplay", "relation": "contains", "confidence": "EXTRACTED", "source_file": "C:\\Users\\maju\\Desktop\\stocks-main\\stocks-main\\client\\src\\utils\\paltiDisplayHelpers.ts", "source_location": "L75", "weight": 1.0}, {"source": "c_users_maju_desktop_stocks_main_stocks_main_client_src_utils_paltidisplayhelpers_ts", "target": "paltidisplayhelpers_getvarietydisplay", "relation": "contains", "confidence": "EXTRACTED", "source_file": "C:\\Users\\maju\\Desktop\\stocks-main\\stocks-main\\client\\src\\utils\\paltiDisplayHelpers.ts", "source_location": "L86", "weight": 1.0}, {"source": "c_users_maju_desktop_stocks_main_stocks_main_client_src_utils_paltidisplayhelpers_ts", "target": "paltidisplayhelpers_getbagsdisplay", "relation": "contains", "confidence": "EXTRACTED", "source_file": "C:\\Users\\maju\\Desktop\\stocks-main\\stocks-main\\client\\src\\utils\\paltiDisplayHelpers.ts", "source_location": "L93", "weight": 1.0}, {"source": "c_users_maju_desktop_stocks_main_stocks_main_client_src_utils_paltidisplayhelpers_ts", "target": "paltidisplayhelpers_getquantitydisplay", "relation": "contains", "confidence": "EXTRACTED", "source_file": "C:\\Users\\maju\\Desktop\\stocks-main\\stocks-main\\client\\src\\utils\\paltiDisplayHelpers.ts", "source_location": "L115", "weight": 1.0}, {"source": "c_users_maju_desktop_stocks_main_stocks_main_client_src_utils_paltidisplayhelpers_ts", "target": "paltidisplayhelpers_getlocationdisplay", "relation": "contains", "confidence": "EXTRACTED", "source_file": "C:\\Users\\maju\\Desktop\\stocks-main\\stocks-main\\client\\src\\utils\\paltiDisplayHelpers.ts", "source_location": "L123", "weight": 1.0}, {"source": "c_users_maju_desktop_stocks_main_stocks_main_client_src_utils_paltidisplayhelpers_ts", "target": "paltidisplayhelpers_getmovementtypedisplay", "relation": "contains", "confidence": "EXTRACTED", "source_file": "C:\\Users\\maju\\Desktop\\stocks-main\\stocks-main\\client\\src\\utils\\paltiDisplayHelpers.ts", "source_location": "L134", "weight": 1.0}, {"source": "c_users_maju_desktop_stocks_main_stocks_main_client_src_utils_paltidisplayhelpers_ts", "target": "paltidisplayhelpers_getrowbackgroundcolor", "relation": "contains", "confidence": "EXTRACTED", "source_file": "C:\\Users\\maju\\Desktop\\stocks-main\\stocks-main\\client\\src\\utils\\paltiDisplayHelpers.ts", "source_location": "L154", "weight": 1.0}, {"source": "c_users_maju_desktop_stocks_main_stocks_main_client_src_utils_paltidisplayhelpers_ts", "target": "paltidisplayhelpers_ispaltimovement", "relation": "contains", "confidence": "EXTRACTED", "source_file": "C:\\Users\\maju\\Desktop\\stocks-main\\stocks-main\\client\\src\\utils\\paltiDisplayHelpers.ts", "source_location": "L170", "weight": 1.0}, {"source": "c_users_maju_desktop_stocks_main_stocks_main_client_src_utils_paltidisplayhelpers_ts", "target": "paltidisplayhelpers_getpaltidisplaydata", "relation": "contains", "confidence": "EXTRACTED", "source_file": "C:\\Users\\maju\\Desktop\\stocks-main\\stocks-main\\client\\src\\utils\\paltiDisplayHelpers.ts", "source_location": "L177", "weight": 1.0}, {"source": "paltidisplayhelpers_getpaltidisplaydata", "target": "paltidisplayhelpers_ispaltimovement", "relation": "calls", "confidence": "EXTRACTED", "source_file": "C:\\Users\\maju\\Desktop\\stocks-main\\stocks-main\\client\\src\\utils\\paltiDisplayHelpers.ts", "source_location": "L178", "weight": 1.0}, {"source": "paltidisplayhelpers_getpaltidisplaydata", "target": "paltidisplayhelpers_getshortagedisplay", "relation": "calls", "confidence": "EXTRACTED", "source_file": "C:\\Users\\maju\\Desktop\\stocks-main\\stocks-main\\client\\src\\utils\\paltiDisplayHelpers.ts", "source_location": "L183", "weight": 1.0}, {"source": "paltidisplayhelpers_getpaltidisplaydata", "target": "paltidisplayhelpers_getpackagingdisplay", "relation": "calls", "confidence": "EXTRACTED", "source_file": "C:\\Users\\maju\\Desktop\\stocks-main\\stocks-main\\client\\src\\utils\\paltiDisplayHelpers.ts", "source_location": "L184", "weight": 1.0}, {"source": "paltidisplayhelpers_getpaltidisplaydata", "target": "paltidisplayhelpers_getbillnumberdisplay", "relation": "calls", "confidence": "EXTRACTED", "source_file": "C:\\Users\\maju\\Desktop\\stocks-main\\stocks-main\\client\\src\\utils\\paltiDisplayHelpers.ts", "source_location": "L185", "weight": 1.0}, {"source": "paltidisplayhelpers_getpaltidisplaydata", "target": "paltidisplayhelpers_getlorrynumberdisplay", "relation": "calls", "confidence": "EXTRACTED", "source_file": "C:\\Users\\maju\\Desktop\\stocks-main\\stocks-main\\client\\src\\utils\\paltiDisplayHelpers.ts", "source_location": "L186", "weight": 1.0}, {"source": "paltidisplayhelpers_getpaltidisplaydata", "target": "paltidisplayhelpers_getvarietydisplay", "relation": "calls", "confidence": "EXTRACTED", "source_file": "C:\\Users\\maju\\Desktop\\stocks-main\\stocks-main\\client\\src\\utils\\paltiDisplayHelpers.ts", "source_location": "L187", "weight": 1.0}, {"source": "paltidisplayhelpers_getpaltidisplaydata", "target": "paltidisplayhelpers_getquantitydisplay", "relation": "calls", "confidence": "EXTRACTED", "source_file": "C:\\Users\\maju\\Desktop\\stocks-main\\stocks-main\\client\\src\\utils\\paltiDisplayHelpers.ts", "source_location": "L188", "weight": 1.0}, {"source": "paltidisplayhelpers_getpaltidisplaydata", "target": "paltidisplayhelpers_getlocationdisplay", "relation": "calls", "confidence": "EXTRACTED", "source_file": "C:\\Users\\maju\\Desktop\\stocks-main\\stocks-main\\client\\src\\utils\\paltiDisplayHelpers.ts", "source_location": "L189", "weight": 1.0}, {"source": "paltidisplayhelpers_getpaltidisplaydata", "target": "paltidisplayhelpers_getmovementtypedisplay", "relation": "calls", "confidence": "EXTRACTED", "source_file": "C:\\Users\\maju\\Desktop\\stocks-main\\stocks-main\\client\\src\\utils\\paltiDisplayHelpers.ts", "source_location": "L191", "weight": 1.0}, {"source": "paltidisplayhelpers_getpaltidisplaydata", "target": "paltidisplayhelpers_getrowbackgroundcolor", "relation": "calls", "confidence": "EXTRACTED", "source_file": "C:\\Users\\maju\\Desktop\\stocks-main\\stocks-main\\client\\src\\utils\\paltiDisplayHelpers.ts", "source_location": "L192", "weight": 1.0}], "raw_calls": [{"caller_nid": "paltidisplayhelpers_getshortagedisplay", "callee": "Number", "source_file": "C:\\Users\\maju\\Desktop\\stocks-main\\stocks-main\\client\\src\\utils\\paltiDisplayHelpers.ts", "source_location": "L16"}, {"caller_nid": "paltidisplayhelpers_getshortagedisplay", "callee": "toFixed", "source_file": "C:\\Users\\maju\\Desktop\\stocks-main\\stocks-main\\client\\src\\utils\\paltiDisplayHelpers.ts", "source_location": "L20"}, {"caller_nid": "paltidisplayhelpers_getshortagedisplay", "callee": "error", "source_file": "C:\\Users\\maju\\Desktop\\stocks-main\\stocks-main\\client\\src\\utils\\paltiDisplayHelpers.ts", "source_location": "L25"}, {"caller_nid": "paltidisplayhelpers_getpackagingdisplay", "callee": "error", "source_file": "C:\\Users\\maju\\Desktop\\stocks-main\\stocks-main\\client\\src\\utils\\paltiDisplayHelpers.ts", "source_location": "L55"}, {"caller_nid": "paltidisplayhelpers_getbagsdisplay", "callee": "error", "source_file": "C:\\Users\\maju\\Desktop\\stocks-main\\stocks-main\\client\\src\\utils\\paltiDisplayHelpers.ts", "source_location": "L107"}, {"caller_nid": "paltidisplayhelpers_getquantitydisplay", "callee": "Number", "source_file": "C:\\Users\\maju\\Desktop\\stocks-main\\stocks-main\\client\\src\\utils\\paltiDisplayHelpers.ts", "source_location": "L116"}, {"caller_nid": "paltidisplayhelpers_getquantitydisplay", "callee": "isNaN", "source_file": "C:\\Users\\maju\\Desktop\\stocks-main\\stocks-main\\client\\src\\utils\\paltiDisplayHelpers.ts", "source_location": "L117"}, {"caller_nid": "paltidisplayhelpers_getquantitydisplay", "callee": "toFixed", "source_file": "C:\\Users\\maju\\Desktop\\stocks-main\\stocks-main\\client\\src\\utils\\paltiDisplayHelpers.ts", "source_location": "L117"}, {"caller_nid": "paltidisplayhelpers_ispaltimovement", "callee": "toLowerCase", "source_file": "C:\\Users\\maju\\Desktop\\stocks-main\\stocks-main\\client\\src\\utils\\paltiDisplayHelpers.ts", "source_location": "L171"}]}