{"nodes": [{"id": "c_users_maju_desktop_stocks_main_stocks_main_server_test_api_js", "label": "test_api.js", "file_type": "code", "source_file": "C:\\Users\\maju\\Desktop\\stocks-main\\stocks-main\\server\\test_api.js", "source_location": "L1"}, {"id": "test_api_testapi", "label": "testApi()", "file_type": "code", "source_file": "C:\\Users\\maju\\Desktop\\stocks-main\\stocks-main\\server\\test_api.js", "source_location": "L8"}], "edges": [{"source": "c_users_maju_desktop_stocks_main_stocks_main_server_test_api_js", "target": "test_api_testapi", "relation": "contains", "confidence": "EXTRACTED", "source_file": "C:\\Users\\maju\\Desktop\\stocks-main\\stocks-main\\server\\test_api.js", "source_location": "L8", "weight": 1.0}], "raw_calls": [{"caller_nid": "test_api_testapi", "callee": "authenticate", "source_file": "C:\\Users\\maju\\Desktop\\stocks-main\\stocks-main\\server\\test_api.js", "source_location": "L9"}, {"caller_nid": "test_api_testapi", "callee": "findOne", "source_file": "C:\\Users\\maju\\Desktop\\stocks-main\\stocks-main\\server\\test_api.js", "source_location": "L12"}, {"caller_nid": "test_api_testapi", "callee": "sign", "source_file": "C:\\Users\\maju\\Desktop\\stocks-main\\stocks-main\\server\\test_api.js", "source_location": "L14"}, {"caller_nid": "test_api_testapi", "callee": "push", "source_file": "C:\\Users\\maju\\Desktop\\stocks-main\\stocks-main\\server\\test_api.js", "source_location": "L25"}, {"caller_nid": "test_api_testapi", "callee": "get", "source_file": "C:\\Users\\maju\\Desktop\\stocks-main\\stocks-main\\server\\test_api.js", "source_location": "L28"}, {"caller_nid": "test_api_testapi", "callee": "push", "source_file": "C:\\Users\\maju\\Desktop\\stocks-main\\stocks-main\\server\\test_api.js", "source_location": "L34"}, {"caller_nid": "test_api_testapi", "callee": "forEach", "source_file": "C:\\Users\\maju\\Desktop\\stocks-main\\stocks-main\\server\\test_api.js", "source_location": "L35"}, {"caller_nid": "test_api_testapi", "callee": "push", "source_file": "C:\\Users\\maju\\Desktop\\stocks-main\\stocks-main\\server\\test_api.js", "source_location": "L40"}, {"caller_nid": "test_api_testapi", "callee": "stringify", "source_file": "C:\\Users\\maju\\Desktop\\stocks-main\\stocks-main\\server\\test_api.js", "source_location": "L40"}, {"caller_nid": "test_api_testapi", "callee": "writeFileSync", "source_file": "C:\\Users\\maju\\Desktop\\stocks-main\\stocks-main\\server\\test_api.js", "source_location": "L43"}, {"caller_nid": "test_api_testapi", "callee": "join", "source_file": "C:\\Users\\maju\\Desktop\\stocks-main\\stocks-main\\server\\test_api.js", "source_location": "L43"}, {"caller_nid": "test_api_testapi", "callee": "log", "source_file": "C:\\Users\\maju\\Desktop\\stocks-main\\stocks-main\\server\\test_api.js", "source_location": "L44"}, {"caller_nid": "test_api_testapi", "callee": "close", "source_file": "C:\\Users\\maju\\Desktop\\stocks-main\\stocks-main\\server\\test_api.js", "source_location": "L45"}]}