{"nodes": [{"id": "c_users_maju_desktop_stocks_main_stocks_main_server_tests_ricestockreportconsistency_test_js", "label": "riceStockReportConsistency.test.js", "file_type": "code", "source_file": "C:\\Users\\maju\\Desktop\\stocks-main\\stocks-main\\server\\__tests__\\riceStockReportConsistency.test.js", "source_location": "L1"}, {"id": "ricestockreportconsistency_test_validatevarietyconsistencyinday", "label": "validateVarietyConsistencyInDay()", "file_type": "code", "source_file": "C:\\Users\\maju\\Desktop\\stocks-main\\stocks-main\\server\\__tests__\\riceStockReportConsistency.test.js", "source_location": "L114"}, {"id": "ricestockreportconsistency_test_validatestandardizedvarietynaming", "label": "validateStandardizedVarietyNaming()", "file_type": "code", "source_file": "C:\\Users\\maju\\Desktop\\stocks-main\\stocks-main\\server\\__tests__\\riceStockReportConsistency.test.js", "source_location": "L164"}, {"id": "ricestockreportconsistency_test_validateoutturntraceability", "label": "validateOutturnTraceability()", "file_type": "code", "source_file": "C:\\Users\\maju\\Desktop\\stocks-main\\stocks-main\\server\\__tests__\\riceStockReportConsistency.test.js", "source_location": "L219"}, {"id": "ricestockreportconsistency_test_validatelegacyvarietyhandling", "label": "validateLegacyVarietyHandling()", "file_type": "code", "source_file": "C:\\Users\\maju\\Desktop\\stocks-main\\stocks-main\\server\\__tests__\\riceStockReportConsistency.test.js", "source_location": "L243"}, {"id": "ricestockreportconsistency_test_validatestockcontinuity", "label": "validateStockContinuity()", "file_type": "code", "source_file": "C:\\Users\\maju\\Desktop\\stocks-main\\stocks-main\\server\\__tests__\\riceStockReportConsistency.test.js", "source_location": "L302"}], "edges": [{"source": "c_users_maju_desktop_stocks_main_stocks_main_server_tests_ricestockreportconsistency_test_js", "target": "ricestockreportconsistency_test_validatevarietyconsistencyinday", "relation": "contains", "confidence": "EXTRACTED", "source_file": "C:\\Users\\maju\\Desktop\\stocks-main\\stocks-main\\server\\__tests__\\riceStockReportConsistency.test.js", "source_location": "L114", "weight": 1.0}, {"source": "c_users_maju_desktop_stocks_main_stocks_main_server_tests_ricestockreportconsistency_test_js", "target": "ricestockreportconsistency_test_validatestandardizedvarietynaming", "relation": "contains", "confidence": "EXTRACTED", "source_file": "C:\\Users\\maju\\Desktop\\stocks-main\\stocks-main\\server\\__tests__\\riceStockReportConsistency.test.js", "source_location": "L164", "weight": 1.0}, {"source": "c_users_maju_desktop_stocks_main_stocks_main_server_tests_ricestockreportconsistency_test_js", "target": "ricestockreportconsistency_test_validateoutturntraceability", "relation": "contains", "confidence": "EXTRACTED", "source_file": "C:\\Users\\maju\\Desktop\\stocks-main\\stocks-main\\server\\__tests__\\riceStockReportConsistency.test.js", "source_location": "L219", "weight": 1.0}, {"source": "c_users_maju_desktop_stocks_main_stocks_main_server_tests_ricestockreportconsistency_test_js", "target": "ricestockreportconsistency_test_validatelegacyvarietyhandling", "relation": "contains", "confidence": "EXTRACTED", "source_file": "C:\\Users\\maju\\Desktop\\stocks-main\\stocks-main\\server\\__tests__\\riceStockReportConsistency.test.js", "source_location": "L243", "weight": 1.0}, {"source": "c_users_maju_desktop_stocks_main_stocks_main_server_tests_ricestockreportconsistency_test_js", "target": "ricestockreportconsistency_test_validatestockcontinuity", "relation": "contains", "confidence": "EXTRACTED", "source_file": "C:\\Users\\maju\\Desktop\\stocks-main\\stocks-main\\server\\__tests__\\riceStockReportConsistency.test.js", "source_location": "L302", "weight": 1.0}], "raw_calls": [{"caller_nid": "ricestockreportconsistency_test_validatevarietyconsistencyinday", "callee": "forEach", "source_file": "C:\\Users\\maju\\Desktop\\stocks-main\\stocks-main\\server\\__tests__\\riceStockReportConsistency.test.js", "source_location": "L119"}, {"caller_nid": "ricestockreportconsistency_test_validatevarietyconsistencyinday", "callee": "forEach", "source_file": "C:\\Users\\maju\\Desktop\\stocks-main\\stocks-main\\server\\__tests__\\riceStockReportConsistency.test.js", "source_location": "L129"}, {"caller_nid": "ricestockreportconsistency_test_validatevarietyconsistencyinday", "callee": "forEach", "source_file": "C:\\Users\\maju\\Desktop\\stocks-main\\stocks-main\\server\\__tests__\\riceStockReportConsistency.test.js", "source_location": "L139"}, {"caller_nid": "ricestockreportconsistency_test_validatevarietyconsistencyinday", "callee": "forEach", "source_file": "C:\\Users\\maju\\Desktop\\stocks-main\\stocks-main\\server\\__tests__\\riceStockReportConsistency.test.js", "source_location": "L149"}, {"caller_nid": "ricestockreportconsistency_test_validatevarietyconsistencyinday", "callee": "log", "source_file": "C:\\Users\\maju\\Desktop\\stocks-main\\stocks-main\\server\\__tests__\\riceStockReportConsistency.test.js", "source_location": "L158"}, {"caller_nid": "ricestockreportconsistency_test_validatestandardizedvarietynaming", "callee": "forEach", "source_file": "C:\\Users\\maju\\Desktop\\stocks-main\\stocks-main\\server\\__tests__\\riceStockReportConsistency.test.js", "source_location": "L169"}, {"caller_nid": "ricestockreportconsistency_test_validatestandardizedvarietynaming", "callee": "forEach", "source_file": "C:\\Users\\maju\\Desktop\\stocks-main\\stocks-main\\server\\__tests__\\riceStockReportConsistency.test.js", "source_location": "L208"}, {"caller_nid": "ricestockreportconsistency_test_validatestandardizedvarietynaming", "callee": "log", "source_file": "C:\\Users\\maju\\Desktop\\stocks-main\\stocks-main\\server\\__tests__\\riceStockReportConsistency.test.js", "source_location": "L213"}, {"caller_nid": "ricestockreportconsistency_test_validateoutturntraceability", "callee": "forEach", "source_file": "C:\\Users\\maju\\Desktop\\stocks-main\\stocks-main\\server\\__tests__\\riceStockReportConsistency.test.js", "source_location": "L222"}, {"caller_nid": "ricestockreportconsistency_test_validateoutturntraceability", "callee": "toBeGreaterThanOrEqual", "source_file": "C:\\Users\\maju\\Desktop\\stocks-main\\stocks-main\\server\\__tests__\\riceStockReportConsistency.test.js", "source_location": "L236"}, {"caller_nid": "ricestockreportconsistency_test_validateoutturntraceability", "callee": "expect", "source_file": "C:\\Users\\maju\\Desktop\\stocks-main\\stocks-main\\server\\__tests__\\riceStockReportConsistency.test.js", "source_location": "L236"}, {"caller_nid": "ricestockreportconsistency_test_validateoutturntraceability", "callee": "log", "source_file": "C:\\Users\\maju\\Desktop\\stocks-main\\stocks-main\\server\\__tests__\\riceStockReportConsistency.test.js", "source_location": "L237"}, {"caller_nid": "ricestockreportconsistency_test_validatelegacyvarietyhandling", "callee": "forEach", "source_file": "C:\\Users\\maju\\Desktop\\stocks-main\\stocks-main\\server\\__tests__\\riceStockReportConsistency.test.js", "source_location": "L248"}, {"caller_nid": "ricestockreportconsistency_test_validatelegacyvarietyhandling", "callee": "log", "source_file": "C:\\Users\\maju\\Desktop\\stocks-main\\stocks-main\\server\\__tests__\\riceStockReportConsistency.test.js", "source_location": "L265"}, {"caller_nid": "ricestockreportconsistency_test_validatelegacyvarietyhandling", "callee": "toFixed", "source_file": "C:\\Users\\maju\\Desktop\\stocks-main\\stocks-main\\server\\__tests__\\riceStockReportConsistency.test.js", "source_location": "L265"}, {"caller_nid": "ricestockreportconsistency_test_validatelegacyvarietyhandling", "callee": "toBe", "source_file": "C:\\Users\\maju\\Desktop\\stocks-main\\stocks-main\\server\\__tests__\\riceStockReportConsistency.test.js", "source_location": "L268"}, {"caller_nid": "ricestockreportconsistency_test_validatelegacyvarietyhandling", "callee": "expect", "source_file": "C:\\Users\\maju\\Desktop\\stocks-main\\stocks-main\\server\\__tests__\\riceStockReportConsistency.test.js", "source_location": "L268"}, {"caller_nid": "ricestockreportconsistency_test_validatestockcontinuity", "callee": "forEach", "source_file": "C:\\Users\\maju\\Desktop\\stocks-main\\stocks-main\\server\\__tests__\\riceStockReportConsistency.test.js", "source_location": "L307"}, {"caller_nid": "ricestockreportconsistency_test_validatestockcontinuity", "callee": "forEach", "source_file": "C:\\Users\\maju\\Desktop\\stocks-main\\stocks-main\\server\\__tests__\\riceStockReportConsistency.test.js", "source_location": "L312"}, {"caller_nid": "ricestockreportconsistency_test_validatestockcontinuity", "callee": "forEach", "source_file": "C:\\Users\\maju\\Desktop\\stocks-main\\stocks-main\\server\\__tests__\\riceStockReportConsistency.test.js", "source_location": "L318"}]}