{"nodes": [{"id": "c_users_maju_desktop_stocks_main_stocks_main_server_routes_admin_users_js", "label": "admin-users.js", "file_type": "code", "source_file": "C:\\Users\\maju\\Desktop\\stocks-main\\stocks-main\\server\\routes\\admin-users.js", "source_location": "L1"}, {"id": "admin_users_normalizename", "label": "normalizeName()", "file_type": "code", "source_file": "C:\\Users\\maju\\Desktop\\stocks-main\\stocks-main\\server\\routes\\admin-users.js", "source_location": "L77"}], "edges": [{"source": "c_users_maju_desktop_stocks_main_stocks_main_server_routes_admin_users_js", "target": "admin_users_normalizename", "relation": "contains", "confidence": "EXTRACTED", "source_file": "C:\\Users\\maju\\Desktop\\stocks-main\\stocks-main\\server\\routes\\admin-users.js", "source_location": "L77", "weight": 1.0}, {"source": "c_users_maju_desktop_stocks_main_stocks_main_server_routes_admin_users_js", "target": "admin_users_normalizename", "relation": "contains", "confidence": "EXTRACTED", "source_file": "C:\\Users\\maju\\Desktop\\stocks-main\\stocks-main\\server\\routes\\admin-users.js", "source_location": "L186", "weight": 1.0}], "raw_calls": [{"caller_nid": "admin_users_normalizename", "callee": "toLowerCase", "source_file": "C:\\Users\\maju\\Desktop\\stocks-main\\stocks-main\\server\\routes\\admin-users.js", "source_location": "L77"}, {"caller_nid": "admin_users_normalizename", "callee": "replace", "source_file": "C:\\Users\\maju\\Desktop\\stocks-main\\stocks-main\\server\\routes\\admin-users.js", "source_location": "L77"}, {"caller_nid": "admin_users_normalizename", "callee": "trim", "source_file": "C:\\Users\\maju\\Desktop\\stocks-main\\stocks-main\\server\\routes\\admin-users.js", "source_location": "L77"}, {"caller_nid": "admin_users_normalizename", "callee": "String", "source_file": "C:\\Users\\maju\\Desktop\\stocks-main\\stocks-main\\server\\routes\\admin-users.js", "source_location": "L77"}, {"caller_nid": "admin_users_normalizename", "callee": "toLowerCase", "source_file": "C:\\Users\\maju\\Desktop\\stocks-main\\stocks-main\\server\\routes\\admin-users.js", "source_location": "L186"}, {"caller_nid": "admin_users_normalizename", "callee": "replace", "source_file": "C:\\Users\\maju\\Desktop\\stocks-main\\stocks-main\\server\\routes\\admin-users.js", "source_location": "L186"}, {"caller_nid": "admin_users_normalizename", "callee": "trim", "source_file": "C:\\Users\\maju\\Desktop\\stocks-main\\stocks-main\\server\\routes\\admin-users.js", "source_location": "L186"}, {"caller_nid": "admin_users_normalizename", "callee": "String", "source_file": "C:\\Users\\maju\\Desktop\\stocks-main\\stocks-main\\server\\routes\\admin-users.js", "source_location": "L186"}]}